detectron3
