Metadata-Version: 2.1
Name: detectron3
Version: 1338.1.0
Summary: Harmless PoC to demonstrate impact of dependency confusion vulnerabilities for the Meta bug bounty program
Author: Your Name
Author-email: your.email@example.com
Classifier: Programming Language :: Python :: 3
Classifier: License :: OSI Approved :: MIT License
Classifier: Operating System :: OS Independent
Requires-Python: >=3.6
